natural_lens/__init__.py
natural_lens/cli.py
natural_lens/profile.py
natural_lens/query.py
natural_lens/databases/__init__.py
natural_lens/databases/base.py
natural_lens/databases/postgres.py
natural_lens/databases/trino.py
natural_lens-0.3.0.dist-info/LICENSE
natural_lens-0.3.0.dist-info/METADATA
natural_lens-0.3.0.dist-info/WHEEL
natural_lens-0.3.0.dist-info/entry_points.txt
natural_lens-0.3.0.dist-info/top_level.txt
natural_lens-0.3.0.dist-info/RECORD
